csvtype_ext.cpython-36m-x86_64-linux-gnu.so
csvtype.libs/libboost_regex-94edd8bd.so.5
csvtype.libs/libicui18n-4a307165.so.36.0
csvtype.libs/libicuuc-9b37ba53.so.36.0
csvtype.libs/libicudata-93d117ac.so.36.0
csvtype/__init__.py
csvtype/patterns.py
csvtype/inferencer.py
csvtype-0.0.2.dist-info/WHEEL
csvtype-0.0.2.dist-info/RECORD
csvtype-0.0.2.dist-info/LICENSE
csvtype-0.0.2.dist-info/top_level.txt
csvtype-0.0.2.dist-info/METADATA
